sync_updown_counter.sv
module sync_updown_counter #(parameter WIDTH=4)(
 input wire clk,
 input wire rst_n,
 input wire enable,
 input wire up,
 input wire load,
 input wire [WIDTH-1:0] load_val,
 output reg [WIDTH-1:0] count
);

 always @(posedge clk or negedge rst_n) begin
    if (!rst_n) begin
      count <= 0;
    end else if (load) begin
      count <= load_val;
    end else if (enable) begin
      count <= up ? count + 1 : count - 1;
    end
 end

endmodule

tb_sync_updown_counter.sv
module tb_sync_updown_counter;
 reg clk;
 reg rst_n;
 reg enable;
 reg up;
 reg load;
 reg [3:0] load_val;
 wire [3:0] count;

 // Instantiate the counter
 sync_updown_counter #(4) counter_inst (
    .clk(clk), .rst_n(rst_n), .enable(enable),
    .up(up), .load(load), .load_val(load_val),
    .count(count)
 );

 // Clock generation
 always #5 clk = ~clk;

 // Test sequence
 initial begin
    clk = 0;
    rst_n = 0;
    enable = 1;
    up = 1;
    load = 0;
    load_val = 4'b0000;
    #10;
    rst_n = 1;
    #10;
    load = 1;
    load_val = 4'b1010;
    #10;
    load = 0;
    #10;
    up = 0;
    #10;
    #50;
    $finish;
 end

 // Monitor
 initial begin
    $monitor("At time %t, count=%b", $time, count);
 end

 // Dump waveforms for viewing
 initial begin
    $dumpfile("waveforms.vcd");
    $dumpvars(0, tb_sync_updown_counter);
 end

endmodule

waveforms.vcd
$date
	Mon Feb  5 20:54:54 2024
$end
$version
	Icarus Verilog
$end
$timescale
	1s
$end
$scope module tb_sync_updown_counter $end
$var wire 4 ! count [3:0] $end
$var reg 1 " clk $end
$var reg 1 # enable $end
$var reg 1 $ load $end
$var reg 4 % load_val [3:0] $end
$var reg 1 & rst_n $end
$var reg 1 ' up $end
$scope module counter_inst $end
$var wire 1 " clk $end
$var wire 1 # enable $end
$var wire 1 $ load $end
$var wire 4 ( load_val [3:0] $end
$var wire 1 & rst_n $end
$var wire 1 ' up $end
$var reg 4 ) count [3:0] $end
$upscope $end
$upscope $end
$enddefinitions $end
#0
$dumpvars
b0 )
b0 (
1'
0&
b0 %
0$
1#
0"
b0 !
$end
#5
1"
#10
0"
1&
#15
b1 !
b1 )
1"
#20
0"
b1010 %
b1010 (
1$
#25
b1010 !
b1010 )
1"
#30
0"
0$
#35
b1011 !
b1011 )
1"
#40
0"
0'
#45
b1010 !
b1010 )
1"
#50
0"
#55
b1001 !
b1001 )
1"
#60
0"
#65
b1000 !
b1000 )
1"
#70
0"
#75
b111 !
b111 )
1"
#80
0"
#85
b110 !
b110 )
1"
#90
0"
#95
b101 !
b101 )
1"
